seismic_forward/__init__.py
seismic_forward/cli.py
seismic_forward/simulation.py
seismic_forward/bin/seismic_forward
seismic_forward.libs/libboost_filesystem-13aca464.so.1.66.0
seismic_forward.libs/libboost_system-bd253e18.so.1.66.0
seismic_forward.libs/libfftw3-6b983104.so.3.5.5
seismic_forward.libs/libgomp-870cb1d0.so.1.0.0
seismic_forward-4.5.0.dist-info/METADATA
seismic_forward-4.5.0.dist-info/WHEEL
seismic_forward-4.5.0.dist-info/entry_points.txt
seismic_forward-4.5.0.dist-info/top_level.txt
seismic_forward-4.5.0.dist-info/RECORD
seismic_forward-4.5.0.dist-info/licenses/LICENCE.md
