Metadata-Version: 2.4
Name: seismic-forward
Version: 4.5.0
Summary: Seismic Forward Modeling Tool
Author: Equinor
Project-URL: Homepage, https://github.com/equinor/seismic-forward
Classifier: Development Status :: 5 - Production/Stable
Classifier: Intended Audience :: Science/Research
Classifier: Programming Language :: Python :: 3
Classifier: Programming Language :: C++
Requires-Python: >=3.11
License-File: LICENCE.md
Provides-Extra: test
Requires-Dist: pytest; extra == "test"
Dynamic: license-file
